runlocal_tools/__init__.py
runlocal_tools/main.py
runlocal_tools/backend/ml_model.py
runlocal_tools/backend/coreml/coreml_model.py
runlocal_tools/backend/onnx/onnx_model.py
runlocal_tools/dtypes/upload.py
runlocal_tools-0.0.2.dist-info/licenses/LICENSE
runlocal_tools-0.0.2.dist-info/METADATA
runlocal_tools-0.0.2.dist-info/WHEEL
runlocal_tools-0.0.2.dist-info/top_level.txt
runlocal_tools-0.0.2.dist-info/RECORD
